doreisa/__init__.py
doreisa/_async_dict.py
doreisa/_scheduler.py
doreisa/_scheduling_actor.py
doreisa/head_node.py
doreisa/simulation_node.py
doreisa/window_api.py
doreisa-0.3.4.dist-info/METADATA
doreisa-0.3.4.dist-info/WHEEL
doreisa-0.3.4.dist-info/RECORD
