Metadata-Version: 2.4
Name: doreisa
Version: 0.3.4
Author-email: Adrien Vannson <adrien.vannson@protonmail.com>
Requires-Python: >=3.12
Requires-Dist: dask[dataframe]==2024.6.0
Requires-Dist: numpy==1.26.4
Requires-Dist: ray[default]<3.0.0,>=2.46.0
